MANIFEST.in
README.md
pyproject.toml
requirements.txt
setup.cfg
setup.py
gcp_airflow_foundations/__init__.py
gcp_airflow_foundations/parse_dags.py
gcp_airflow_foundations/version.py
gcp_airflow_foundations/base_class/__init__.py
gcp_airflow_foundations/base_class/column_udf_config.py
gcp_airflow_foundations/base_class/data_source_table_config.py
gcp_airflow_foundations/base_class/dataflow_job_config.py
gcp_airflow_foundations/base_class/dlp_source_config.py
gcp_airflow_foundations/base_class/dlp_table_config.py
gcp_airflow_foundations/base_class/facebook_config.py
gcp_airflow_foundations/base_class/facebook_table_config.py
gcp_airflow_foundations/base_class/file_source_config.py
gcp_airflow_foundations/base_class/file_table_config.py
gcp_airflow_foundations/base_class/hds_metadata_config.py
gcp_airflow_foundations/base_class/hds_table_config.py
gcp_airflow_foundations/base_class/landing_zone_config.py
gcp_airflow_foundations/base_class/ods_metadata_config.py
gcp_airflow_foundations/base_class/ods_table_config.py
gcp_airflow_foundations/base_class/salesforce_ingestion_config.py
gcp_airflow_foundations/base_class/schema_options_config.py
gcp_airflow_foundations/base_class/sftp_source_config.py
gcp_airflow_foundations/base_class/sftp_table_config.py
gcp_airflow_foundations/base_class/source_base_config.py
gcp_airflow_foundations/base_class/source_config.py
gcp_airflow_foundations/base_class/source_ingestion_config.py
gcp_airflow_foundations/base_class/source_table_config.py
gcp_airflow_foundations/base_class/source_template_config.py
gcp_airflow_foundations/base_class/template_ingestion_options_config.py
gcp_airflow_foundations/base_class/utils.py
gcp_airflow_foundations/common/__init__.py
gcp_airflow_foundations/common/dataflow/__init__.py
gcp_airflow_foundations/common/dataflow/dataflow_taskgroups.py
gcp_airflow_foundations/common/dataflow/jdbc/__init__.py
gcp_airflow_foundations/common/dataflow/jdbc/mysql/__init__.py
gcp_airflow_foundations_dev.egg-info/PKG-INFO
gcp_airflow_foundations_dev.egg-info/SOURCES.txt
gcp_airflow_foundations_dev.egg-info/dependency_links.txt
gcp_airflow_foundations_dev.egg-info/requires.txt
gcp_airflow_foundations_dev.egg-info/top_level.txt