Metadata-Version: 2.1
Name: gcp-airflow-foundations-dev
Version: 11
Summary: Opinionated framework based on Airflow 2.0 for building pipelines to ingest data into a BigQuery data warehouse
Home-page: https://github.com/badal-io/gcp-airflow-foundations
Author: Badal.io
Author-email: info@badal.io
License: Apache 2.0
Platform: UNKNOWN
Classifier: Development Status :: 4 - Beta
Classifier: Intended Audience :: Developers
Classifier: Topic :: Software Development :: Libraries
Classifier: License :: OSI Approved :: Apache Software License
Classifier: Programming Language :: Python :: 3.6
Classifier: Programming Language :: Python :: 3.7
Classifier: Programming Language :: Python :: 3.8
Classifier: Programming Language :: Python :: 3.9
